trueseeing/__init__.py
trueseeing/api.py
trueseeing/py.typed
trueseeing/app/__init__.py
trueseeing/app/inspect.py
trueseeing/app/scan.py
trueseeing/app/shell.py
trueseeing/app/cmd/__init__.py
trueseeing/app/cmd/alias.py
trueseeing/app/cmd/analyze.py
trueseeing/app/cmd/config.py
trueseeing/app/cmd/info.py
trueseeing/app/cmd/report.py
trueseeing/app/cmd/scan.py
trueseeing/app/cmd/search.py
trueseeing/app/cmd/show.py
trueseeing/app/cmd/android/__init__.py
trueseeing/app/cmd/android/asm.py
trueseeing/app/cmd/android/engage.py
trueseeing/app/cmd/android/recon.py
trueseeing/app/cmd/android/search.py
trueseeing/app/cmd/android/show.py
trueseeing/app/cmd/ios/__init__.py
trueseeing/app/cmd/ios/engage.py
trueseeing/app/cmd/ios/recon.py
trueseeing/core/__init__.py
trueseeing/core/analyze.py
trueseeing/core/config.py
trueseeing/core/context.py
trueseeing/core/cvss.py
trueseeing/core/db.py
trueseeing/core/env.py
trueseeing/core/exc.py
trueseeing/core/ext.py
trueseeing/core/nat.py
trueseeing/core/report.py
trueseeing/core/scan.py
trueseeing/core/store.py
trueseeing/core/tools.py
trueseeing/core/ui.py
trueseeing/core/z.py
trueseeing/core/android/asm.py
trueseeing/core/android/context.py
trueseeing/core/android/db.py
trueseeing/core/android/device.py
trueseeing/core/android/model.py
trueseeing/core/android/store.py
trueseeing/core/android/tools.py
trueseeing/core/android/analyze/__init__.py
trueseeing/core/android/analyze/flow.py
trueseeing/core/android/analyze/nat.py
trueseeing/core/android/analyze/op.py
trueseeing/core/ios/__init__.py
trueseeing/core/ios/analyze.py
trueseeing/core/ios/context.py
trueseeing/core/ios/db.py
trueseeing/core/ios/device.py
trueseeing/core/ios/model.py
trueseeing/core/ios/store.py
trueseeing/core/ios/swift.py
trueseeing/core/model/__init__.py
trueseeing/core/model/cmd.py
trueseeing/core/model/issue.py
trueseeing/core/model/sig.py
trueseeing/libs/LICENSE.md
trueseeing/libs/files.0.sql
trueseeing/libs/public_suffix_list.dat
trueseeing/libs/store.0.sql
trueseeing-2.2.8.dist-info/entry_points.txt
trueseeing-2.2.8.dist-info/licenses/COPYING
trueseeing-2.2.8.dist-info/WHEEL
trueseeing-2.2.8.dist-info/METADATA
trueseeing-2.2.8.dist-info/RECORD
