Metadata-Version: 2.4
Name: trueseeing
Version: 2.2.8
Summary: Trueseeing is a non-decompiling iOS/Android application vulnerability scanner.
Keywords: ios,android,security,pentest,hacking
Author-email: Takahiro Yoshimura <alterakey@protonmail.com>
Requires-Python: >=3.9
Classifier: Topic :: Security
Classifier: Environment :: Console
Classifier: Operating System :: POSIX :: Linux
Classifier: Operating System :: POSIX :: BSD
Classifier: Operating System :: MacOS :: MacOS X
Classifier: Operating System :: Android
Classifier: License :: OSI Approved :: GNU General Public License v3 or later (GPLv3+)
License-File: COPYING
Requires-Dist: aiohttp~=3.9
Requires-Dist: asn1crypto~=1.5
Requires-Dist: frida-tools~=13.6
Requires-Dist: importlib-metadata~=7.0
Requires-Dist: jinja2~=3.1
Requires-Dist: lief~=0.14
Requires-Dist: lxml~=5.0
Requires-Dist: progressbar2~=4.3
Requires-Dist: prompt-toolkit~=3.0
Requires-Dist: pyaxmlparser~=0.3
Requires-Dist: pypubsub~=4.0
Requires-Dist: pyyaml~=6.0
Requires-Dist: pyzstd~=0.16
Requires-Dist: termcolor~=2.4
Project-URL: Source, https://github.com/alterakey/trueseeing
